cfb/__init__.py
cfb/cli.py
cfb/constants.py
cfb/context.py
cfb/generator.py
cfb/namespace.py
cfb/struct.py
cfb/test_cli.py
cfb/test_context.py
cfb/test_namespace.py
cfb/test_struct.py
cfb/version.py
cfb/reflection/BaseType.py
cfb/reflection/Enum.py
cfb/reflection/EnumVal.py
cfb/reflection/Field.py
cfb/reflection/KeyValue.py
cfb/reflection/Object.py
cfb/reflection/RPCCall.py
cfb/reflection/Schema.py
cfb/reflection/Service.py
cfb/reflection/Type.py
cfb/reflection/__init__.py
cfb/reflection/test_Schema.py
cfb/templates/_builder_mod.rs.jinja
cfb/templates/_flatbuffers_verifier_mod.rs.jinja
cfb/templates/_legacy_verifier_mod.rs.jinja
cfb/templates/builder.rs.jinja
cfb/templates/flatbuffers_verifier.rs.jinja
cfb/templates/legacy_verifier.rs.jinja
cfbc-0.1.9.data/scripts/cfbc
cfbc-0.1.9.dist-info/LICENSE
cfbc-0.1.9.dist-info/METADATA
cfbc-0.1.9.dist-info/WHEEL
cfbc-0.1.9.dist-info/top_level.txt
cfbc-0.1.9.dist-info/RECORD
