Metadata-Version: 2.1
Name: cfbc
Version: 0.1.9
Summary: CFB code generator
Home-page: http://github.com/nervosnetwork/cfb
Author: Nervos Core Dev
Author-email: dev@nervos.org
License: MIT
Platform: UNKNOWN
Classifier: Development Status :: 2 - Pre-Alpha
Classifier: Environment :: Console
Requires-Dist: docopt
Requires-Dist: Jinja2
Requires-Dist: flatbuffers
